snooker/__init__.py
snooker/api/__init__.py
snooker/api/base.py
snooker/api/snooker_org.py
snooker/models/__init__.py
snooker/models/snooker_org/__init__.py
snooker/models/snooker_org/event.py
snooker/models/snooker_org/match.py
snooker/models/snooker_org/player.py
snooker/models/snooker_org/ranking.py
snooker/models/snooker_org/round.py
snooker/models/snooker_org/seeding.py
snooker-0.6.0.dist-info/LICENSE
snooker-0.6.0.dist-info/METADATA
snooker-0.6.0.dist-info/WHEEL
snooker-0.6.0.dist-info/top_level.txt
snooker-0.6.0.dist-info/RECORD
