Metadata-Version: 2.1
Name: snooker
Version: 0.6.0
Summary: Snooker Data API
Home-page: https://www.github.com/mgorsk1/snooker
Maintainer: mgorsk1
Maintainer-email: gorskimariusz13@gmail.com
Classifier: Programming Language :: Python :: 3.6
Classifier: Programming Language :: Python :: 3.7
Classifier: Programming Language :: Python :: 3.8
Requires-Python: >=3.6
License-File: LICENSE
Requires-Dist: dataclasses-json
Requires-Dist: requests
